python-egardia/__init__.py
python-egardia/python-egardia.py
pythonegardia/__init__.py
pythonegardia/egardiadevice.py
pythonegardia/egardiaserver.py
pythonegardia/test_egardiadevice.py
pythonegardia/test_egardiaserver.py
pythonegardia-1.0.50.dist-info/METADATA
pythonegardia-1.0.50.dist-info/WHEEL
pythonegardia-1.0.50.dist-info/top_level.txt
pythonegardia-1.0.50.dist-info/zip-safe
pythonegardia-1.0.50.dist-info/RECORD
