Metadata-Version: 2.1
Name: pythonegardia
Version: 1.0.50
Summary: Python 3 support for Egardia / Woonveilig alarm
Home-page: https://github.com/jeroenterheerdt/python-egardia
Author: Jeroen ter Heerdt
License: MIT
Platform: UNKNOWN
Requires-Dist: requests (>=2.0)
